{
    "list_variables": [],
    "mixins": [],
    "resource_name": "EC2_Security_Group_Rule_Property_Type",
    "ruby_class_name": "SecurityGroupRulePropertyType",
    "ruby_class_name_underscore": "security_group_rule_property_type",
    "ruby_comment_name": "EC2_Security_Group_Rule_Property_Type",
    "topic_title": "EC2 Security Group Rule Property Type",
    "url": "http://docs.aws.amazon.com/AWSCloudFormation/latest/UserGuide/aws-properties-ec2-security-group-rule.html",
    "variables": [
        {
            "name": "CidrIp",
            "name_underscore": "cidr_ip",
            "required": "Conditional If you specify\n                     SourceSecurityGroupName or\n                     SourceSecurityGroupId, do not specify\n                     CidrIp.",
            "type": "String"
        },
        {
            "name": "DestinationSecurityGroupId (SecurityGroupEgress only)",
            "name_underscore": "destination_security_group_id (security_group_egress only)",
            "required": "Conditional Cannot be used when specifying a CIDR IP address.",
            "type": "String"
        },
        {
            "name": "FromPort",
            "name_underscore": "from_port",
            "required": "Yes",
            "type": "Integer"
        },
        {
            "name": "IpProtocol",
            "name_underscore": "ip_protocol",
            "required": "Yes",
            "type": "String"
        },
        {
            "name": "SourceSecurityGroupId (SecurityGroupIngress only)",
            "name_underscore": "source_security_group_id (security_group_ingress only)",
            "required": "Conditional. If you specify CidrIp, do not specify\n                     SourceSecurityGroupId.",
            "type": "String"
        },
        {
            "name": "SourceSecurityGroupName (SecurityGroupIngress only)",
            "name_underscore": "source_security_group_name (security_group_ingress only)",
            "required": "Conditional. If you specify CidrIp, do not\n                  specify SourceSecurityGroupName.",
            "type": "String"
        },
        {
            "name": "SourceSecurityGroupOwnerId (SecurityGroupIngress only)",
            "name_underscore": "source_security_group_owner_id (security_group_ingress only)",
            "required": "Conditional. If you specify\n                     SourceSecurityGroupName and that security group is owned\n                  by a different account than the account creating the stack, you must specify the\n                     SourceSecurityGroupOwnerId; otherwise, this property is\n                  optional.",
            "type": "String"
        },
        {
            "name": "ToPort",
            "name_underscore": "to_port",
            "required": "Yes",
            "type": "Integer"
        }
    ]
}